lightsolver_lib/__init__.py
lightsolver_lib/lightsolver_lib.py
lightsolver_lib-0.7.0.dist-info/licenses/LICENSE
lightsolver_lib-0.7.0.dist-info/METADATA
lightsolver_lib-0.7.0.dist-info/WHEEL
lightsolver_lib-0.7.0.dist-info/top_level.txt
lightsolver_lib-0.7.0.dist-info/RECORD
