Metadata-Version: 2.4
Name: lightsolver-lib
Version: 0.7.0
Summary: Tools for developers using LightSolver's Cloud Platform
Author-email: Matan Arkin <matan@lightsolver.com>
Project-URL: Homepage, https://lightsolver.com
Classifier: Programming Language :: Python :: 3
Classifier: License :: OSI Approved :: Apache Software License
Classifier: Operating System :: OS Independent
Requires-Python: >=3.8
License-File: LICENSE
Requires-Dist: numpy==1.26.4
Requires-Dist: plotly
Dynamic: license-file
